pygeoshader/__init__.py
pygeoshader/load_raster.py
pygeoshader-0.1.0a1.dist-info/LICENSE
pygeoshader-0.1.0a1.dist-info/METADATA
pygeoshader-0.1.0a1.dist-info/WHEEL
pygeoshader-0.1.0a1.dist-info/RECORD
