Metadata-Version: 2.1
Name: pygeoshader
Version: 0.1.0a1
Summary: Python package for 3D mapping
License: MIT
Author: James Gardiner
Author-email: james@jgardiner.co.uk
Requires-Python: >=3.11,<4.0
Classifier: License :: OSI Approved :: MIT License
Classifier: Programming Language :: Python :: 3
Classifier: Programming Language :: Python :: 3.11
Requires-Dist: rasterio (>=1.3.7,<2.0.0)
